molecularprofiles/__init__.py
molecularprofiles/_version.py
molecularprofiles/molecularprofiles.py
molecularprofiles/version.py
molecularprofiles/_dev_version/__init__.py
molecularprofiles/tests/test_grib_utils.py
molecularprofiles/tests/test_humidity.py
molecularprofiles/tests/test_molecular_profiles.py
molecularprofiles/tests/test_profile_utils.py
molecularprofiles/tests/test_rayleigh.py
molecularprofiles/tests/test_data/__init__.py
molecularprofiles/tests/test_data/absorbing_molecules_tests/__init__.py
molecularprofiles/tests/test_data/absorbing_molecules_tests/sample_cams_molecules.grib
molecularprofiles/tests/test_data/absorbing_molecules_tests/sample_ozone.grib
molecularprofiles/tests/test_data/ecsv/__init__.py
molecularprofiles/tests/test_data/ecsv/test_rayleigh_extinction_file.ecsv
molecularprofiles/tests/test_data/grib/__init__.py
molecularprofiles/tests/test_data/grib/sample.grib
molecularprofiles/tests/test_data/grib/sample2.grib2
molecularprofiles/tests/test_data/reference_atmospheres_tests/__init__.py
molecularprofiles/tests/test_data/reference_atmospheres_tests/reference_atmo_model_v0_CTA-south_winter.ecsv
molecularprofiles/utils/__init__.py
molecularprofiles/utils/constants.py
molecularprofiles/utils/grib_utils.py
molecularprofiles/utils/humidity.py
molecularprofiles/utils/logger.conf
molecularprofiles/utils/profiles_utils.py
molecularprofiles/utils/rayleigh.py
molecularprofiles/utils/absorbing_molecules/nitrogen_dioxide_absorption_cross_section_294K.ecsv
molecularprofiles/utils/absorbing_molecules/ozone_cross_section_293K.ecsv
molecularprofiles/utils/models/upper_atmospheres/upper_atmosphere_north_intermediate.ecsv
molecularprofiles/utils/models/upper_atmospheres/upper_atmosphere_north_summer.ecsv
molecularprofiles/utils/models/upper_atmospheres/upper_atmosphere_north_winter.ecsv
molecularprofiles/utils/models/upper_atmospheres/upper_atmosphere_south_summer.ecsv
molecularprofiles/utils/models/upper_atmospheres/upper_atmosphere_south_winter.ecsv
molecularprofiles-3.0.0.dist-info/licenses/LICENSE
molecularprofiles-3.0.0.dist-info/METADATA
molecularprofiles-3.0.0.dist-info/WHEEL
molecularprofiles-3.0.0.dist-info/top_level.txt
molecularprofiles-3.0.0.dist-info/RECORD
