Metadata-Version: 2.4
Name: molecularprofiles
Version: 3.0.0
Summary: Meteorological data analysis suite
Author-email: Pere Munar Adrover <pere.munar@uab.cat>, Markus Gaug <markus.gaug@uab.cat>, Scott Griffiths <sgriffiths@ifae.es>, Georgios Voutsinas <georgios.voutsinas@unige.ch>, Mykhailo Dalchenko <mykhailo.dalchenko@unige.ch>
License: Copyright (c) 2020, Molecularprofiles Project
Project-URL: Home, https://gitlab.cta-observatory.org/cta-array-elements/ccf/mdps
Project-URL: Doc, http://cta-array-elements.gitlab-pages.cta-observatory.org/ccf/MDPs/
Classifier: License :: OSI Approved :: BSD License
Requires-Python: >=3.11
License-File: LICENSE
Requires-Dist: numpy
Requires-Dist: scipy
Requires-Dist: astropy
Requires-Dist: pygrib
Provides-Extra: test
Requires-Dist: pytest; extra == "test"
Requires-Dist: pytest-cov; extra == "test"
Requires-Dist: pylint>=2.15; extra == "test"
Requires-Dist: black>=22.5; extra == "test"
Requires-Dist: coverage-badge; extra == "test"
Provides-Extra: doc
Requires-Dist: sphinx; extra == "doc"
Requires-Dist: numpydoc; extra == "doc"
Requires-Dist: pydata-sphinx-theme; extra == "doc"
Requires-Dist: myst-parser; extra == "doc"
Requires-Dist: sphinx-paramlinks; extra == "doc"
Requires-Dist: sphinx-argparse; extra == "doc"
Requires-Dist: nbsphinx; extra == "doc"
Requires-Dist: sphinx-design; extra == "doc"
Requires-Dist: linkify-it-py; extra == "doc"
Requires-Dist: ipykernel; extra == "doc"
Provides-Extra: dev
Requires-Dist: pre-commit; extra == "dev"
Requires-Dist: setuptools_scm[toml]; extra == "dev"
Provides-Extra: all
Requires-Dist: molecularprofiles[dev,doc,test]; extra == "all"
Dynamic: license-file
